MANIFEST.in
README.rst
setup.py
Products/__init__.py
Products.flickrgallery.egg-info/PKG-INFO
Products.flickrgallery.egg-info/SOURCES.txt
Products.flickrgallery.egg-info/dependency_links.txt
Products.flickrgallery.egg-info/entry_points.txt
Products.flickrgallery.egg-info/namespace_packages.txt
Products.flickrgallery.egg-info/not-zip-safe
Products.flickrgallery.egg-info/requires.txt
Products.flickrgallery.egg-info/top_level.txt
Products/flickrgallery/AppConfig.py
Products/flickrgallery/TODO.txt
Products/flickrgallery/__init__.py
Products/flickrgallery/cleanup.sh
Products/flickrgallery/config.py
Products/flickrgallery/interfaces.py
Products/flickrgallery/refresh.txt
Products/flickrgallery/version.txt
Products/flickrgallery/Extensions/__init__.py
Products/flickrgallery/content/.FlickrGallery.py.swp
Products/flickrgallery/content/FlickrGallery.py
Products/flickrgallery/content/__init__.py
Products/flickrgallery/content/flickrengine/__init__.py
Products/flickrgallery/content/flickrengine/flickrengine.py
Products/flickrgallery/content/flickrengine/flickrlib.py
Products/flickrgallery/content/flickrengine/flickrtest.py
Products/flickrgallery/i18n/generated.pot
Products/flickrgallery/model/flickrgallery.zargo
Products/flickrgallery/profiles/default/cssregistry.xml
Products/flickrgallery/profiles/default/jsregistry.xml
Products/flickrgallery/profiles/default/metadata.xml
Products/flickrgallery/profiles/default/skins.xml
Products/flickrgallery/profiles/default/types.xml
Products/flickrgallery/profiles/default/types/.FlickrGallery.xml.swo
Products/flickrgallery/profiles/default/types/FlickrGallery.xml
Products/flickrgallery/skins/flickrgallery/arrowLeft.gif
Products/flickrgallery/skins/flickrgallery/arrowRight.gif
Products/flickrgallery/skins/flickrgallery/flickrgallery.colorbox.js
Products/flickrgallery/skins/flickrgallery/flickrgallery.css.dtml
Products/flickrgallery/skins/flickrgallery/flickrgallery.png
Products/flickrgallery/skins/flickrgallery/flickrgallery_variables.js.pt
Products/flickrgallery/skins/flickrgallery/flickrgallery_view.pt
Products/flickrgallery/skins/flickrgallery/image_details.pt
Products/flickrgallery/skins/flickrgallery/image_view_fullscreen.pt
Products/flickrgallery/skins/flickrgallery/macFFBgHack.png
Products/flickrgallery/skins/flickrgallery/portlet_categories.pt
Products/flickrgallery/skins/flickrgallery/readme.txt
