Metadata-Version: 1.1
Name: Products.flickrgallery
Version: 1.1.1
Summary: A Gallery product for Plone, powered by Flickr
Home-page: https://github.com/collective/Products.flickrgallery
Author: David Bain
Author-email: david@alteroo.com
License: GPL
Keywords: flickr,photogallery
Platform: UNKNOWN
Classifier: Framework :: Plone
Classifier: Programming Language :: Python
Classifier: Programming Language :: Python :: 2.6
Classifier: Programming Language :: Python :: 2.7
